README.rst
setup.cfg
setup.py
drf_scaffolding/__init__.py
drf_scaffolding/management/__init__.py
drf_scaffolding/management/commands/__init__.py
drf_scaffolding/management/commands/createadmin.py
drf_scaffolding/management/commands/createapi.py
drf_scaffolding/management/commands/createforms.py
drf_scaffolding/management/commands/createserializers.py
drf_scaffolding/management/commands/hocus_pocus.py
drf_scaffolding/management/commands/settings.py
drf_scaffolding/management/commands/templates.py
drf_scaffolding/management/commands/utils.py
drfscaffolding.egg-info/PKG-INFO
drfscaffolding.egg-info/SOURCES.txt
drfscaffolding.egg-info/dependency_links.txt
drfscaffolding.egg-info/requires.txt
drfscaffolding.egg-info/top_level.txt