Metadata-Version: 1.1
Name: drfscaffolding
Version: 0.2.1
Summary: Django app which allow create full APIs based on your models defined in your project.
Home-page: https://angellagunas.github.io/drf-scaffolding/
Author: Angel Lagunas
Author-email: angel.david.lagunas@gmail.com
License: UNKNOWN
Download-URL: https://github.com/angellagunas/drf-scaffolding/archive/0.1.tar.gz
Platform: UNKNOWN
Classifier: Framework :: Django
